defillama2/__init__.py
defillama2/defillama2.py
defillama2/scratch.py
defillama2-0.7.5.dist-info/LICENSE
defillama2-0.7.5.dist-info/METADATA
defillama2-0.7.5.dist-info/WHEEL
defillama2-0.7.5.dist-info/top_level.txt
defillama2-0.7.5.dist-info/RECORD
