Metadata-Version: 2.1
Name: defillama2
Version: 0.7.5
Summary: Python client for DefiLlama API
Home-page: https://github.com/coindataschool/defillama2
Author: Coin Data School
Author-email: <coindataschool@gmail.com>
Keywords: python 3,defillama,api
Classifier: Programming Language :: Python :: 3
Classifier: Programming Language :: Python :: 3.6
Classifier: Programming Language :: Python :: 3.7
Classifier: Programming Language :: Python :: 3.8
Classifier: Programming Language :: Python :: 3.9
Classifier: Programming Language :: Python :: 3.10
Classifier: License :: OSI Approved :: MIT License
Classifier: Operating System :: OS Independent
License-File: LICENSE
Requires-Dist: requests (>=2.28.1)
Requires-Dist: pandas (>=1.4.4)
Requires-Dist: numpy (>=1.22.4)
